{
    "author_id": 116602510771,
    "comments_disabled": false,
    "created_at": "2018-04-18T09:31:10Z",
    "draft": false,
    "edited_at": "2019-11-08T09:47:06Z",
    "html_url": "https://help.memsource.com/hc/en-us/articles/360002841231-Pre-translate-Jobs",
    "id": 360002841231,
    "label_names": [
        "pre-translate",
        "disable AI matches",
        "_SPRVD"
    ],
    "locale": "en-us",
    "name": "Pre-translate Jobs",
    "outdated": false,
    "outdated_locales": [],
    "permission_group_id": 592372,
    "position": 27,
    "promoted": false,
    "section_id": 115000903671,
    "source_locale": "en-us",
    "title": "Pre-translate Jobs",
    "updated_at": "2019-11-08T09:47:06Z",
    "url": "https://memsource.zendesk.com/api/v2/help_center/en-us/articles/360002841231-Pre-translate-Jobs.json",
    "user_segment_id": null,
    "vote_count": 0,
    "vote_sum": 0
}