{
    "author_id": 116990862271,
    "comments_disabled": false,
    "created_at": "2018-05-18T16:37:18Z",
    "draft": false,
    "edited_at": "2019-10-13T15:53:11Z",
    "html_url": "https://help.memsource.com/hc/en-us/articles/360004056431-Searching-and-Filtering-in-Memsource-Mobile",
    "id": 360004056431,
    "label_names": [
        "search and replace",
        "_RWD",
        "_addIMG"
    ],
    "locale": "en-us",
    "name": "Searching and Filtering in Memsource Mobile",
    "outdated": false,
    "outdated_locales": [],
    "permission_group_id": 592372,
    "position": 2,
    "promoted": false,
    "section_id": 115000919491,
    "source_locale": "en-us",
    "title": "Searching and Filtering in Memsource Mobile",
    "updated_at": "2019-10-13T15:53:11Z",
    "url": "https://memsource.zendesk.com/api/v2/help_center/en-us/articles/360004056431-Searching-and-Filtering-in-Memsource-Mobile.json",
    "user_segment_id": null,
    "vote_count": 0,
    "vote_sum": 0
}