{
    "author_id": 116990862271,
    "comments_disabled": false,
    "created_at": "2018-05-07T18:34:10Z",
    "draft": false,
    "edited_at": "2019-05-28T12:01:27Z",
    "html_url": "https://help.memsource.com/hc/en-us/articles/360003466931-TYPO3-Plugin",
    "id": 360003466931,
    "label_names": [
        "_RWD",
        "connectors",
        "connector",
        "_addIMG"
    ],
    "locale": "en-us",
    "name": "TYPO3 Plugin",
    "outdated": false,
    "outdated_locales": [],
    "permission_group_id": 592352,
    "position": 7,
    "promoted": false,
    "section_id": 360000691772,
    "source_locale": "en-us",
    "title": "TYPO3 Plugin",
    "updated_at": "2019-05-28T12:01:27Z",
    "url": "https://memsource.zendesk.com/api/v2/help_center/en-us/articles/360003466931-TYPO3-Plugin.json",
    "user_segment_id": null,
    "vote_count": 0,
    "vote_sum": 0
}