{
    "author_id": 373846258851,
    "comments_disabled": false,
    "created_at": "2019-10-11T08:29:03Z",
    "draft": false,
    "edited_at": "2019-11-08T09:45:25Z",
    "html_url": "https://help.memsource.com/hc/en-us/articles/360009928819-October-15-2019-Memsource-Editor-for-Desktop-Release-v6-239-6",
    "id": 360009928819,
    "label_names": [],
    "locale": "en-us",
    "name": "October 15, 2019: Memsource Editor for Desktop Release v6.239.6",
    "outdated": false,
    "outdated_locales": [],
    "permission_group_id": 592352,
    "position": 0,
    "promoted": false,
    "section_id": 360001133271,
    "source_locale": "en-us",
    "title": "October 15, 2019: Memsource Editor for Desktop Release v6.239.6",
    "updated_at": "2019-11-08T09:45:25Z",
    "url": "https://memsource.zendesk.com/api/v2/help_center/en-us/articles/360009928819-October-15-2019-Memsource-Editor-for-Desktop-Release-v6-239-6.json",
    "user_segment_id": null,
    "vote_count": 0,
    "vote_sum": 0
}